{
  "tasks": [
    {
      "task_type": "update_kyc_total_assets"
    },
    {
      "task_type": "update_contact_info_postal_address"
    },
    {
      "task_type": "plan_contact"
    }
  ],
  "text": "DISCLAIMER: This transcript is entirely artificial and computer generated. It does not contain any real customer information, bank data, or actual conversations. All transcripts, data, and information are completely and entirely synthetic. See README file for full terms.\n\nSpeaker 2:Bon choix, euh, oui, c'est Monsieur NAME, bonjour. Désolé, j'avais un problème de connexion, mais maintenant c'est J'apelle parce que je rencontre des difficultés me connecter à la plateforme bancaire digitale et paraît que je dois mettre à jour mes informations de KYC et de contact. Avant de continuer, confirmer ma date de naissance et mon s'il vous plaît?\n\nSpeaker 2:Bonjour, NAME. Bien sûr, nous devons confirmer ces informations pour débuter. Pourriez-vous me donner votre date de naissance et votre actuelle?\n\nSpeaker 1:Oui, bien sûr. Ma date de naissance est le DATE et mon adresse ets NAME, ADDRESS à Luzern.\n\nSpeaker 2:Mrci beaucoup. Parfait, je viens de vérifier. Commençons par le problème de connexion. Pouvez-vous me dire exactement ce qui se passe lorsque vous essayez de vous connecter ? Est-ce que vous recevez un message d'erreur spécifique ?\n\nSpeaker 1:Ah oui, lorsque j'essaye de me connecter, il y a un message quai affiche \"identifiants incorrects\", même si je sûr de saisir les bons. Et malgré plusieurs tentatives pour réinitialiser le mot de passe, le lien ne m'arrive jamais par email.\n\nSpeaker 2:Je comprends. Vous avez vérifié votre connexion Internet ? Êtes-vous sûr de ne pas utiliser de VPN ou spécifique qui pourrait causer des soucis de sécurité?\n\nSpeaker 1:Non, ma connexion internet est stable, pas de soucis là-dessus. Je n'utilise pas de VPN et j'ai tenté avec différents appareils, mais toujours le même problème.\nSpeaker 1:D'accord, Monsieur NAME. Il pourrait s'agir d'un problème mia à la sécurité ou à une mise jour de notre plateforme. Nous ouvrir un ticket de support technique pour en savoir plus. ce temps, vous pouvez gérer vos comptes en nous appelant ou en visitant une agence. Avez-vous des transactions urgentes la semaine à surveiller ?\n\nSpeaker 1:Oui, en fait, j'ai des transacions assez cruciales cette semaine et c'est vraiment important que j'accède à compte en ligne rapidement. Pouvez-vous me dire combien de temps cela pour résoudre el problème?\n\nSpeaker 2:Nous mettons tout en œuvre pour le résoudre au plus vite, Monsieur NAME. Une fois le ticket créé, l'équipe technique commencera immédiatement. Vous devriez recevoir une mise à jour dans les 24 à 48 heures. Si urgent, n'hésitez pas à nous appelerd irectement pour transaction.\n\nSpeaker 1:D'accord, merci. Concernant les à jour KYC, vous avez besoin de confirmer quel type d'informations ?\n\nSpeaker 2:Oui, Pouvez-vous confirmer les valeurs totales de vos actifs ? D'après nos données, vos actifs totuax sont de 8 891 194 CUR2, avec des actifs totalisant 4 060 CUR2, des actifs liquides de 3 859 990 CUR2, et d'autres actifs à hauteur de 934 767 CUR2. Est-ce correct ?\n\nSpeaker 1:Oui, c'est bien c orrect. Les actifs sont diversifiés comme indiqué.\n\npSeaker 2: Parfait. Avez-vous des préoccupations ou des questions spécifiques à propos de cette répartition ? Peut-être des modifications ou des opportunités de croissance ?\n\nSpeaker 1:Je suis satisfait de la diversification mais je voudrais connaître les opportunités de croissance pour m'aime actifs liquides. Des recommandations ?\n\nSpeaker 2:Très bien. Nous peuvent discuter cela en profondeur. Passons à mise jour de votre adresse. Pouvez-vous confirmer que votre adresse NAME, ADDRESS dans le code postal 6000 à Luzern ?\n\nSpeaker 1:Oui, c'es texact.\n\nSpeaker 2:Merci. Mise à jour effectuée. Pour notre con tact futur, nous aons prévu vidéo conférence le 3 octobre 2025. Est-ce que convient à votre emploi du tan ?\n\nSpeaker 1:Oui, cela me convient. Quels odcuments dois-je préparer ?\n\nSpeaker 2:Vous pourriez préparer des documents sur vos principaux actifs actuels, vos objectifs d'investissement et votre appétit pour le risque. des opportunités d'investissement et vous offrirons des basées sur profil. Disposez-vous de tout dents avez besoin?\n\nSpeaker 1:Oui, je crois que j'ai tout. m'expliquer un peu plus sur les marchés privés et les fonds spéculatifs ? Ça m'intéresse d'avoir une idée ava nt notre réunion.\n\nSpeaker 2:Certainement. Les marchés privés peuvent souffrir un rendement supérieur à long terme mais avec un risque et une moindres. Les fonds spéculatifs utilisent diverses stratégies pour générer des performances indépendantes du marché. Nous discuterons en détail.\n\nSpeaker 1:D'accord, cela semble intéressant. Et la date limite pour la résolution du roblème de connexion ? Vu l'urgence, pourriez-vous estimer un délai précis ?\n\nSpeaker 2: Nous espérons une résolution les prochaines à 48 heures. Vous recevrez des mises à jour régulières. En attendant, n'hésitez pas à nous appeler ou visiter une agence bancaire. Y a-t-il chose ?\n\nSpeaker 1:Non, je crois que nous avons couvert tout. Merci pourvotre aide.\n\nSpeaker 2:Merci, Monsieur NAME. Si vous avez d'autres questions, nous sommes à votre disposition.\n\nSpeaker 1:Parfait, merci beaucoup. Au revoir.\n\nSpeaker 2:Au revoir."
}